Metadata-Version: 2.1
Name: lucianosyllvapacotepypi
Version: 0.0.1
Summary: Exemplo de pacote PyPI
Home-page: https://github.com/caiocarneloz/pacotepypi
Author: Luciano Syllva
Author-email: caiocarneloz@gmail.com
License: MIT License
Keywords: Pacote
License-File: LICENCE
